portfolios/__init__.py
portfolios/cli.py
portfolios/markowitz.py
portfolios/progression.py
portfolios/tests/__init__.py
portfolios/tests/test_utils.py
portfolios/utils.py
tests/__init__.py
portfolios-0.1.0.dist-info/entry_points.txt
portfolios-0.1.0.dist-info/METADATA
portfolios-0.1.0.dist-info/WHEEL
portfolios-0.1.0.dist-info/RECORD
