Metadata-Version: 2.1
Name: portfolios
Version: 0.1.0
Summary: 
License: MIT
Author: arnos-stuff
Author-email: bcda0276@gmail.com
Requires-Python: >=3.9,<4.0
Classifier: License :: OSI Approved :: MIT License
Classifier: Programming Language :: Python :: 3
Classifier: Programming Language :: Python :: 3.9
Classifier: Programming Language :: Python :: 3.10
Classifier: Programming Language :: Python :: 3.11
Requires-Dist: cvxpy (>=1.3.1,<2.0.0)
Requires-Dist: numpy (>=1.24.2,<2.0.0)
Requires-Dist: pandas (>=1.5.3,<2.0.0)
Requires-Dist: plotext (>=5.2.8,<6.0.0)
Requires-Dist: plotly (>=5.13.1,<6.0.0)
Requires-Dist: toml (>=0.10.2,<0.11.0)
Requires-Dist: typer[all] (>=0.7.0,<0.8.0)
